LICENSE
MANIFEST.in
README.md
requirements.txt
setup.py
parrots/__init__.py
parrots/asr.py
parrots/chinese_utils.py
parrots/cli.py
parrots/cnhubert.py
parrots/english_utils.py
parrots/japanese_utils.py
parrots/log.py
parrots/mel_processing.py
parrots/patched_mha_with_cache.py
parrots/pinyin2hanzi.py
parrots/symbols.py
parrots/synthesizer_model.py
parrots/synthesizer_utils.py
parrots/t2s_model.py
parrots/t2s_utils.py
parrots/text_utils.py
parrots/tone_sandhi.py
parrots/tts.py
parrots/utils.py
parrots/wav_util.py
parrots.egg-info/PKG-INFO
parrots.egg-info/SOURCES.txt
parrots.egg-info/dependency_links.txt
parrots.egg-info/entry_points.txt
parrots.egg-info/not-zip-safe
parrots.egg-info/requires.txt
parrots.egg-info/top_level.txt
parrots/data/.DS_Store
parrots/data/cmudict.rep
parrots/data/cmudict_cache.pickle
parrots/data/opencpop-strict.txt
parrots/data/pinyin2hanzi/char_idx.txt
parrots/data/pinyin2hanzi/dic_pinyin.txt
parrots/data/pinyin2hanzi/mapping.json
parrots/data/pinyin2hanzi/pinyin_hanzi_dict.txt
parrots/data/pinyin2hanzi/word_idx.txt
parrots/data/voice/小严-电台男主播-中文普通话-青年男声.mp3
parrots/data/voice/沈毅-沉稳高管-中文普通话-中年男声.mp3
parrots/data/voice/瑞恩-磁性中年男声-美式口音.mp3
parrots/data/voice/薇薇-傲娇御姐-中文普通话-青年女声.mp3
parrots/data/voice/阿志-活泼深情男声-中文粤语.mp3
parrots/indextts/README.md
parrots/indextts/__init__.py
parrots/indextts/inference.py
parrots/indextts/BigVGAN/ECAPA_TDNN.py
parrots/indextts/BigVGAN/__init__.py
parrots/indextts/BigVGAN/activations.py
parrots/indextts/BigVGAN/bigvgan.py
parrots/indextts/BigVGAN/models.py
parrots/indextts/BigVGAN/utils.py
parrots/indextts/BigVGAN/alias_free_activation/__init__.py
parrots/indextts/BigVGAN/alias_free_activation/cuda/__init__.py
parrots/indextts/BigVGAN/alias_free_activation/cuda/activation1d.py
parrots/indextts/BigVGAN/alias_free_activation/cuda/anti_alias_activation.cpp
parrots/indextts/BigVGAN/alias_free_activation/cuda/anti_alias_activation_cuda.cu
parrots/indextts/BigVGAN/alias_free_activation/cuda/compat.h
parrots/indextts/BigVGAN/alias_free_activation/cuda/load.py
parrots/indextts/BigVGAN/alias_free_activation/cuda/type_shim.h
parrots/indextts/BigVGAN/alias_free_activation/torch/__init__.py
