Metadata-Version: 2.4
Name: parrots
Version: 1.2.5
Summary: Parrots, Automatic Speech Recognition(**ASR**), Text-To-Speech(**TTS**) toolkit
Home-page: https://github.com/shibing624/parrots
Author: XuMing
Author-email: xuming624@qq.com
License: Apache 2.0
Keywords: TTS,ASR,text to speech,speech
Platform: Windows
Platform: Linux
Platform: Solaris
Platform: Mac OS-X
Platform: Unix
Classifier: Intended Audience :: Developers
Classifier: Operating System :: OS Independent
Classifier: Natural Language :: Chinese (Simplified)
Classifier: Natural Language :: Chinese (Traditional)
Classifier: Programming Language :: Python
Classifier: Programming Language :: Python :: 3
Classifier: Topic :: Software Development :: Libraries :: Python Modules
Classifier: Topic :: Scientific/Engineering :: Artificial Intelligence
Requires-Python: >=3.8.0
License-File: LICENSE
Requires-Dist: pypinyin
Requires-Dist: jieba
Requires-Dist: loguru
Requires-Dist: transformers
Requires-Dist: huggingface_hub
Requires-Dist: librosa
Requires-Dist: nltk
Requires-Dist: g2p_en
Requires-Dist: cn2an
Requires-Dist: zh-normalization
Requires-Dist: einops
Requires-Dist: soundfile
Requires-Dist: fire
Requires-Dist: tqdm
Requires-Dist: descript-audiotools
Requires-Dist: torchaudio
Requires-Dist: munch
Requires-Dist: wetext
Requires-Dist: pandas
Requires-Dist: sentencepiece
Dynamic: author
Dynamic: author-email
Dynamic: classifier
Dynamic: description
Dynamic: description-content-type
Dynamic: home-page
Dynamic: keywords
Dynamic: license
Dynamic: license-file
Dynamic: platform
Dynamic: requires-dist
Dynamic: requires-python
Dynamic: summary
